Workbook

Sheet PI
A1: PROFORMA INVOICE
A2: MURLI STEEL CORPORATION
H3: Original for Buyer/ Seller/ Transporter
A4: 9/12, Lal Bazar Street, Mercantile Building, 'B' Block, 1st Floor, Kolkata - 700001, India
A5: Phone: (033) 2210 1650 | Mobile: 9830242818 | Email: shradkakrania@gmail.com
A6: PAN: AKAPK4846L | GSTIN: 19AKAPK4846L1ZS
A8: BILLED TO PARTY | E8: INVOICE DETAILS
A9: Name: | C9: Lagan Engineering Co. Ltd. | E9: Invoice No.: | G9: MSC/PI03/2026-27
A10: Address: | C10: 14 KYD Street, Kolkata - 700016 | E10: Invoice Date: | G10: 46217
A11: GSTIN: | C11: 19AAACT9986F1ZP | E11: Payment Terms | G11: PROFORMA INVOICE
A12: Order No. | C12: P/2627/1388 | E12: Place of Supply: | G12: West Bengal
A13: Order Date | C13: 46204
A14: State: | B14: West Bengal | C14: Code: 19
A16: Delivery At: Lagan Engineering Co. Ltd., c/o Angus Jute Mills, Bhadeshwar, W.B. | E16: Transport: Lorry | G16: Vehicel No. :
A18: SN | B18: Item Code | C18: Description | D18: HSN Code | E18: No. of Pcs. | F18: Qty (kg) | G18: Rate (INR/kg) | H18: Taxable Value (INR)
A19: 1 | B19: =Master_Items!B7 -> 09113BL | C19: =Master_Items!C20 -> BRIGHT M.S. 1.31/32" (50MM) DIA. TOLERANCE -0.001"/-0.004" (En3B-BS970:1955) | D19: 721550 | F19: 560 | G19: 70 | H19: =F19*G19 -> 39200
A20: 2 | B20: =Master_Items!B2 -> 09112BL | C20: =Master_Items!C2 -> BRIGHT M.S. 1.3/4" DIA. TOLERANCE ON DIA. -0.002"/-0.005". LENGTH: 19-20 FEET (En3B-BS970:1955) | D20: 721550 | F20: 1070 | G20: 70 | H20: =F20*G20 -> 74900
A21: 3 | B21: =Master_Items!B7 -> 09113BL | C21: =Master_Items!C7 -> BRIGHT M.S. 2" DIA. TOLERANCE ON DIA. +0.005"/+0.008". LENGTH: 18.5 FEET (En3B-BS970:1955) | D21: 721550 | F21: 540 | G21: 70 | H21: =F21*G21 -> 37800
A22: 4 | B22: =Master_Items!B13 -> 09158BL | C22: =Master_Items!C13 -> BRIGHT M.S. GB 45MM DIA. TOLERANCE ON DIA. | D22: 721550 | F22: 1020 | G22: 70 | H22: =F22*G22 -> 71400
A23: 5 | B23: =Master_Items!B7 -> 09113BL | C23: =Master_Items!C7 -> BRIGHT M.S. 2" DIA. TOLERANCE ON DIA. +0.005"/+0.008". LENGTH: 18.5 FEET (En3B-BS970:1955) | D23: 721550 | F23: 2100 | G23: 70 | H23: =F23*G23 -> 147000
A24: 6 | B24: =Master_Items!B23 -> 09332BL | C24: =Master_Items!C23 -> BRIGHT M.S. GB 5/8" DIA. TOLERANCE +0.008"/+0.012" | D24: 721550 | F24: 530 | G24: 71 | H24: =F24*G24 -> 37630
A25: 7 | B25: =Master_Items!B21 -> 09816BL | C25: =Master_Items!C21 -> 1.3/8" DIA BRIGHT CLASS IV STEEL (G.B) TOL ON DIA +0.008"/+0.012" | D25: 721550 | F25: 1995 | G25: 85 | H25: =F25*G25 -> 169575
A26: 8 | B26: =Master_Items!B27 -> 09246BL | C26: =Master_Items!C27 -> M.S. CHANNEL 3" X 1.1/2" (75X40MM), LENGTH: 20-22 FT | F26: 1550 | G26: 60 | H26: =F26*G26 -> 93000
E28: Total Amount Before Tax | H28: =SUM(H19:H26) -> 670505
E29: Delivery Charges | H29: 16500
E30: Taxable Value | H30: =SUM(H28:H29) -> 687005
E31: Add: CGST @ 9% | H31: =$H$30*9% -> 61830.45
E32: Add: SGST @ 9% | H32: =$H$30*9% -> 61830.45
E33: Grand Total | H33: =SUM(H30:H32) -> 810665.9
A35: Total Invoice Amount in Words: Eight Lakh Ten Thousand Six Hundred Sixty-Five Rupees and Ninety Paise only.
A37: Bank Details : | H37: Certified that the particulars given above are true and correct.
A38: Bank: | C38: HDFC Bank Ltd. | E38: For MURLI STEEL CORPORATION
A39: A/c No.: | C39: 00082000057539
A40: Branch: | C40: Sree Bhumi
A41: IFSC: | C41: HDFC0004566 | E41: Authorised Signatory
A43: Terms: Goods once sold will not be taken back. Interest may be charged on delayed payment. Subject to Kolkata jurisdiction.
A44: E & O.E.

Sheet Master_Items
A1: Sl No. | B1: Part No | C1: Item Description | D1: HSN Code
A2: =IF(B2<>"", 1, "") -> 1 | B2: 09112BL | C2: BRIGHT M.S. 1.3/4" DIA. TOLERANCE ON DIA. -0.002"/-0.005". LENGTH: 19-20 FEET (En3B-BS970:1955) | D2: 721550
A3: =IF(B2<>"", COUNTA(B$2:$B3), "") -> 2 | B3: 09118BL | C3: BRIGHT M.S. 1/2" DIA. TOLERANCE ON DIA. -0.001"/-0.003". LENGTH: 18-20 FEET (En3B-BS970:1955) | D3: 721550
A4: =IF(B3<>"", COUNTA(B$2:$B4), "") -> 3 | B4: 09119BL | C4: BRIGHT M.S. 5/8" DIA. TOLERANCE ON DIA. -0.001"/-0.003". LENGTH: 18-20 FEET (En3B-BS970:1955) | D4: 721550
A5: =IF(B4<>"", COUNTA(B$2:$B5), "") -> 4 | B5: 09304BL | C5: BRIGHT M.S. 7/8" DIA. TOLERANCE ON DIA. -0.001"/-0.003". LENGTH: 11-15 FEET (En3B-BS970:1955) | D5: 721550
A6: =IF(B5<>"", COUNTA(B$2:$B6), "") -> 5 | B6: 09336BL | C6: BRIGHT M.S. FLAT 1" X 1/2" (25X12MM) | D6: 721550
A7: =IF(B6<>"", COUNTA(B$2:$B7), "") -> 6 | B7: 09113BL | C7: BRIGHT M.S. 2" DIA. TOLERANCE ON DIA. +0.005"/+0.008". LENGTH: 18.5 FEET (En3B-BS970:1955) | D7: 721550
A8: =IF(B7<>"", COUNTA(B$2:$B8), "") -> 7 | B8: 09114BL | C8: BRIGHT M.S. 2.1/4" DIA. TOLERANCE ON DIA. +0.005"/+0.008". LENGTH: 18.5 FEET (En3B-BS970:1955) | D8: 721550
A9: =IF(B8<>"", COUNTA(B$2:$B9), "") -> 8 | B9: 09283BL | C9: BRIGHT M.S. 1.1/2" DIA. TOLERANCE ON DIA. -0.002"/-0.005". LENGTH: 18-20 FEET (En3B-BS970:1955) | D9: 721550
A10: =IF(B9<>"", COUNTA(B$2:$B10), "") -> 9 | B10: 09822BL | C10: BRIGHT CK45 STEEL - 2.1/4" DIA. GB TOL ON OD +0.014"/+0.018", HARDNESS 204 TO 249 BHN | D10: 721550
A11: =IF(B10<>"", COUNTA(B$2:$B11), "") -> 10 | B11: 09850BL | C11: 2.204" DIA. BRIGHT MS BAR - DIA. TOLERANCE +0.005"/+0.008" (En3B-BS970:1955) | D11: 721550
A12: =IF(B11<>"", COUNTA(B$2:$B12), "") -> 11 | B12: 09831BL | C12: BRIGHT MS 3" DIA. TOLERANCE +000/-0.004". LENGTH: 8 TO 10 FEET (En3B-BS970:1955) | D12: 721550
A13: =IF(B12<>"", COUNTA(B$2:$B13), "") -> 12 | B13: 09158BL | C13: BRIGHT M.S. GB 45MM DIA. TOLERANCE ON DIA. | D13: 721550
A14: =IF(B13<>"", COUNTA(B$2:$B14), "") -> 13 | B14: 09110BL | C14: BRIGHT M.S. 1" DIA. TOLERANCE -0.005"/-0.008". LENGTH: 8-12 FT (En3B-BS970:1955) | D14: 721550
... A24: =IF(B23<>"", COUNTA(B$2:$B24), "") -> 23 | B24: 09307BL | C24: 0.820" A/F HEXAGONAL BR. MS BAR (En3B-BS970:1955) | D24: 721550
A25: =IF(B24<>"", COUNTA(B$2:$B25), "") -> 24 | B25: 09394BL | C25: BLACK M.S. FLAT 40 X 12 MM
A26: =IF(B25<>"", COUNTA(B$2:$B26), "") -> 25 | B26: 09428BL | C26: BLACK M.S. FLAT 50 X 12 MM
A27: =IF(B26<>"", COUNTA(B$2:$B27), "") -> 26 | B27: 09246BL | C27: M.S. CHANNEL 3" X 1.1/2" (75X40MM), LENGTH: 20-22 FT
A28: =IF(B27<>"", COUNTA(B$2:$B28), "") -> 27 | B28: 09256BL | C28: M.S. CHANNEL 4" X 2" (100X50MM), LENGTH: 18 FT
A29: =IF(B28<>"", COUNTA(B$2:$B29), "") -> 28 | B29: 09427BL | C29: M.S. ANGLE 3" X 3" X 1/4" (75X75X6 MM), LENGTH: 18-20 FT
A30: =IF(B29<>"", COUNTA(B$2:$B30), "") -> 29 | B30: 09437BL | C30: BLACK M.S. ROUND 100 MM DIA - HARDNESS 150 TO 180 BHN (En3B-BS970:1955)
A31: =IF(B30<>"", COUNTA(B$2:$B31), "") -> 30 | B31: 09380BL | C31: BLACK M.S. 125 MM DIA - HARDNESS 150 TO 180 BHN (En3B-BS970:1955)
A32: =IF(B31<>"", COUNTA(B$2:$B32), "") -> 31 | B32: 09442BL | C32: EN31 FLAT 40 X 25 MM | D32: 722860
A33: =IF(B32<>"", COUNTA(B$2:$B33), "") -> 32 | B33: 09451BL | C33: EN31 FLAT 40 X 20 MM | D33: 722860
A34: =IF(B33<>"", COUNTA(B$2:$B34), "") -> 33 | B34: 09423BL | C34: SEAMLESS STEEL TUBE 1.15/16" X 1.1/2"
A35: =IF(B34<>"", COUNTA(B$2:$B35), "") -> 33 | C35: 105MM CARBON STEEL En-8 ROUND | D35: 721410
A36: 34 | B36: 09516BL | C36: 85MM DIA. EN-8 ROUND | D36: 721410
A37: =IF(B36<>"", COUNTA(B$2:$B37), "") -> 35 | B37: 09517BL | C37: 75MM DIA. EN-8 ROUND | D37: 721410
A38: =IF(B37<>"", COUNTA(B$2:$B38), "") -> 36 | B38: 61131BL | C38: 70MM DIA. EN-8 ROUND | D38: 721410
A39: =IF(B38<>"", COUNTA(B$2:$B39), "") -> 37 | B39: 09520BL | C39: 65MM EN8 ROUND BAR | D39: 721410
A40: =IF(B39<>"", COUNTA(B$2:$B40), "") -> 38 | B40: 09330BL | C40: DIA 130 MM EN-24 BLACK ROUND BAR | D40: 722830
A41: =IF(B40<>"", COUNTA(B$2:$B41), "") -> 39 | B41: 09329BL | C41: DIA 110 MM EN-24 BLACK ROUND BAR | D41: 722830
A42: =IF(B41<>"", COUNTA(B$2:$B42), "") -> 40 | B42: 09326BL | C42: DIA 90 MM EN-24 BLACK ROUND BAR | D42: 722830
A43: =IF(B42<>"", COUNTA(B$2:$B43), "") -> 41 | B43: 12050038 | C43: G.I. FLAT 50 X 6mm | D43: 72123010
A44: =IF(B43<>"", COUNTA(B$2:$B44), "") -> 42 | B44: 12050041 | C44: G.I. FLAT 25 X 3mm | D44: 72123010
A45: =IF(B44<>"", COUNTA(B$2:$B45), "") -> 43 | B45: 12050059 | C45: G.I. FLAT 19 X 3mm | D45: 72123010
A46: =IF(B45<>"", COUNTA(B$2:$B46), "") -> 44 | B46: 12050040 | C46: G.I. FLAT 25 X 6mm | D46: 72123010

Sheet Lagan_19
A1: TAX INVOICE
A2: MURLI STEEL CORPORATION
H3: Original for Buyer/ Seller/ Transporter
A4: 9/12, Lal Bazar Street, Mercantile Building, 'B' Block, 1st Floor, Kolkata - 700001, India
A5: Phone: (033) 2210 1650 | Mobile: 9830242818 | Email: shradkakrania@gmail.com
A6: PAN: AKAPK4846L | GSTIN: 19AKAPK4846L1ZS
A8: BILLED TO PARTY | E8: INVOICE DETAILS
A9: Name: | C9: Lagan Engineering Co. Ltd. | E9: Invoice No.: | G9: MSC/19/2026-27
A10: Address: | C10: 14 KYD Street, Kolkata - 700016 | E10: Invoice Date: | G10: 46239
A11: GSTIN: | C11: 19AAACT9986F1ZP | E11: Payment Terms | G11: PROFROMA INVOICE
A12: Order No. | C12: P/2627/1388 | E12: Place of Supply: | G12: West Bengal
A13: Order Date | C13: 46204
A14: State: | B14: West Bengal | C14: Code: 19
A16: Delivery At: Lagan Engineering Co. Ltd., c/o Angus Jute Mills, Bhadeshwar, W.B. | E16: Transport: Lorry | G16: Vehicel No. : WB 15C 5843
A18: SN | B18: Item Code | C18: Description | D18: HSN Code | E18: No. of Pcs. | F18: Qty (kg) | G18: Rate (INR/kg) | H18: Taxable Value (INR)
A19: 1 | B19: =Master_Items!B20 -> 09083BL | C19: =Master_Items!C20 -> BRIGHT M.S. 1.31/32" (50MM) DIA. TOLERANCE -0.001"/-0.004" (En3B-BS970:1955) | D19: 721550 | E19: 6 | F19: 575 | G19: 70 | H19: =F19*G19 -> 40250
A20: 2 | B20: =Master_Items!B2 -> 09112BL | C20: =Master_Items!C2 -> BRIGHT M.S. 1.3/4" DIA. TOLERANCE ON DIA. -0.002"/-0.005". LENGTH: 19-20 FEET (En3B-BS970:1955) | D20: 721550 | E20: 14 | F20: 1029 | G20: 70 | H20: =F20*G20 -> 72030
A21: 3 | B21: =Master_Items!B7 -> 09113BL | C21: =Master_Items!C7 -> BRIGHT M.S. 2" DIA. TOLERANCE ON DIA. +0.005"/+0.008". LENGTH: 18.5 FEET (En3B-BS970:1955) | D21: 721550 | E21: 6 | F21: 582 | G21: 70 | H21: =F21*G21 -> 40740
A22: 4 | B22: =Master_Items!B13 -> 09158BL | C22: =Master_Items!C13 -> BRIGHT M.S. GB 45MM DIA. TOLERANCE ON DIA. | D22: 721550 | E22: 15 | F22: 1107 | G22: 70 | H22: =F22*G22 -> 77490
A23: 5 | B23: =Master_Items!B9 -> 09283BL | C23: =Master_Items!C9 -> BRIGHT M.S. 1.1/2" DIA. TOLERANCE ON DIA. -0.002"/-0.005". LENGTH: 18-20 FEET (En3B-BS970:1955) | D23: 721550 | E23: 36 | F23: 2032 | G23: 70 | H23: =F23*G23 -> 142240
A24: 6 | B24: =Master_Items!B23 -> 09332BL | C24: =Master_Items!C23 -> BRIGHT M.S. GB 5/8" DIA. TOLERANCE +0.008"/+0.012" | D24: 721550 | E24: 50 | F24: 506 | G24: 71 | H24: =F24*G24 -> 35926
A25: 7 | B25: =Master_Items!B21 -> 09816BL | C25: =Master_Items!C21 -> 1.3/8" DIA BRIGHT CLASS IV STEEL (G.B) TOL ON DIA +0.008"/+0.012" | D25: 721550 | E25: 36 | F25: 1974 | G25: 85 | H25: =F25*G25 -> 167790
A26: 8 | B26: =Master_Items!B27 -> 09246BL | C26: =Master_Items!C27 -> M.S. CHANNEL 3" X 1.1/2" (75X40MM), LENGTH: 20-22 FT | D26: 721610 | E26: 39 | F26: 1480 | G26: 60 | H26: =F26*G26 -> 88800
C27: TOTAL: | E27: =SUM(E19:E26) -> 202 | F27: =SUM(F19:F26) -> 9285
E29: Total Amount Before Tax | H29: =SUM(H19:H26) -> 665266
E30: Delivery Charges | H30: 16500
E31: Taxable Value | H31: =SUM(H29:H30) -> 681766
E32: Add: CGST @ 9% | H32: =$H$31*9% -> 61358.94
E33: Add: SGST @ 9% | H33: =$H$31*9% -> 61358.94
E34: Grand Total | H34: =SUM(H31:H33) -> 804483.88
A36: Total Invoice Amount in Words: Eight Lakh Four Thousand Four Hundred Eighty-Three Rupees and Eighty-Eight Paise only.
A38: Bank Details : | H38: Certified that the particulars given above are true and correct.
A39: Bank: | C39: HDFC Bank Ltd. | E39: For MURLI STEEL CORPORATION
A40: A/c No.: | C40: 00082000057539
A41: Branch: | C41: Sree Bhumi
A42: IFSC: | C42: HDFC0004566 | E42: Authorised Signatory
A44: Terms: Goods once sold will not be taken back. Interest may be charged on delayed payment. Subject to Kolkata jurisdiction.
A45: E & O.E.

Sheet Lagan_17
A1: TAX INVOICE
A2: MURLI STEEL CORPORATION
H3: Original for Buyer/ Seller/ Transporter
A4: 9/12, Lal Bazar Street, Mercantile Building, 'B' Block, 1st Floor, Kolkata - 700001, India
A5: Phone: (033) 2210 1650 | Mobile: 9830242818 | Email: shradkakrania@gmail.com
A6: PAN: AKAPK4846L | GSTIN: 19AKAPK4846L1ZS
A8: BILLED TO PARTY | E8: INVOICE DETAILS
A9: Name: | C9: Lagan Engineering Co. Ltd. | E9: Invoice No.: | G9: MSC/18/2026-27
A10: Address: | C10: 14 KYD Street, Kolkata - 700016 | E10: Invoice Date: | G10: 46225
A11: GSTIN: | C11: 19AAACT9986F1ZP | E11: Payment Terms | G11: AGAINST DELIVERY
A12: Order No. | C12: TELEPHONIC | E12: Place of Supply: | G12: West Bengal
A13: Order Date | C13: 46224
A14: State: | B14: West Bengal | C14: Code: 19
A16: Delivery At: Lagan Engineering Co. Ltd., c/o Angus Jute Mills, Bhadeshwar, W.B. | E16: Transport: Lorry | G16: Vehicel No. : NL01 AE 9616
A18: SN | B18: Item Code | C18: Description | D18: HSN Code | E18: No. of Pcs. | F18: Qty (kg) | G18: Rate (INR/kg) | H18: Taxable Value (INR)
A19: 1 | B19: =Master_Items!B29 -> 09427BL | C19: M.S. ANGLE | D19: 72162100 | F19: 1025 | G19: 70 | H19: =F19*G19 -> 71750
A20: 2 | C20: M.S. ANGLE | D20: 72165000 | F20: 1299 | G20: 70 | H20: =F20*G20 -> 90930
A21: 3 | B21: 09246BL | C21: M.S. CHANNEL | D21: 72165000 | F21: 1033 | G21: 70 | H21: =F21*G21 -> 72310
A22: 4 | C22: M.S. SQUARE | D22: 72142090 | F22: 1100 | G22: 60 | H22: =F22*G22 -> 66000
C23: TOTAL WEIGHT: | F23: =SUM(F19:F22) -> 4457
E25: Total Amount Before Tax | H25: =SUM(H19:H23) -> 300990
E26: Delivery Charges
E27: Taxable Value | H27: =SUM(H25:H26) -> 300990
E28: Add: CGST @ 9% | H28: =$H$27*9% -> 27089.1
E29: Add: SGST @ 9% | H29: =$H$27*9% -> 27089.1
E30: Grand Total | H30: =SUM(H27:H29) -> 355168.2
A32: Total Invoice Amount in Words: Three Lakh Fifty-Five Thousand One Hundred Sixty-Eight Rupees and Twenty Paise ONLY.
A34: Bank Details : | H34: Certified that the particulars given above are true and correct.
A35: Bank: | C35: HDFC Bank Ltd. | E35: For MURLI STEEL CORPORATION
A36: A/c No.: | C36: 00082000057539
A37: Branch: | C37: Sree Bhumi
A38: IFSC: | C38: HDFC0004566 | E38: Authorised Signatory
A40: Terms: Goods once sold will not be taken back. Interest may be charged on delayed payment. Subject to Kolkata jurisdiction.
A41: E & O.E.

Sheet Lagan_16
A1: TAX INVOICE
A2: MURLI STEEL CORPORATION
H3: Original for Buyer/ Seller/ Transporter
A4: 9/12, Lal Bazar Street, Mercantile Building, 'B' Block, 1st Floor, Kolkata - 700001, India
A5: Phone: (033) 2210 1650 | Mobile: 9830242818 | Email: shradkakrania@gmail.com
A6: PAN: AKAPK4846L | GSTIN: 19AKAPK4846L1ZS
A8: BILLED TO PARTY | E8: INVOICE DETAILS
A9: Name: | C9: Lagan Engineering Co. Ltd. | E9: Invoice No.: | G9: MSC/16/2026-27
A10: Address: | C10: 14 KYD Street, Kolkata - 700016 | E10: Invoice Date: | G10: 46212
A11: GSTIN: | C11: 19AAACT9986F1ZP | E11: Payment Terms | G11: PROFORMA INVOICE
A12: Order No. | C12: P/2627/1388 | E12: Place of Supply: | G12: West Bengal
A13: Order Date | C13: 46204
A14: State: | B14: West Bengal | C14: Code: 19
A16: Delivery At: Lagan Engineering Co. Ltd., c/o Angus Jute Mills, Bhadeshwar, W.B. | E16: Transport: Lorry | G16: Vehicel No. : WB 15C 3317
A18: SN | B18: Item Code | C18: Description | D18: HSN Code | E18: No. of Pcs. | F18: Qty (kg) | G18: Rate (INR/kg) | H18: Taxable Value (INR)
A19: 1 | B19: =Master_Items!B7 -> 09113BL | C19: =Master_Items!C7 -> BRIGHT M.S. 2" DIA. TOLERANCE ON DIA. +0.005"/+0.008". LENGTH: 18.5 FEET (En3B-BS970:1955) | D19: 721550 | F19: 1025 | G19: 70 | H19: =F19*G19 -> 71750
A20: 2 | B20: =Master_Items!B13 -> 09158BL | C20: =Master_Items!C13 -> BRIGHT M.S. GB 45MM DIA. TOLERANCE ON DIA. | D20: 721550 | F20: 1299 | G20: 70 | H20: =F20*G20 -> 90930
A21: 3 | B21: =Master_Items!B9 -> 09283BL | C21: =Master_Items!C9 -> BRIGHT M.S. 1.1/2" DIA. TOLERANCE ON DIA. -0.002"/-0.005". LENGTH: 18-20 FEET (En3B-BS970:1955) | D21: 721550 | F21: 1033 | G21: 70 | H21: =F21*G21 -> 72310
A22: 4 | B22: =Master_Items!B27 -> 09246BL | C22: M.S. CHANNEL 3" X 1.1/2" (75X40MM) | D22: 721610 | F22: 1100 | G22: 60 | H22: =F22*G22 -> 66000
C23: TOTAL WEIGHT: | F23: =SUM(F19:F22) -> 4457
E25: Total Amount Before Tax | H25: =SUM(H19:H23) -> 300990
E26: Delivery Charges
E27: Taxable Value | H27: =SUM(H25:H26) -> 300990
E28: Add: CGST @ 9% | H28: =$H$27*9% -> 27089.1
E29: Add: SGST @ 9% | H29: =$H$27*9% -> 27089.1
E30: Grand Total | H30: =SUM(H27:H29) -> 355168.2
A32: Total Invoice Amount in Words: Three Lakh Fifty-Five Thousand One Hundred Sixty-Eight Rupees and Twenty Paise ONLY.
A34: Bank Details : | H34: Certified that the particulars given above are true and correct.
A35: Bank: | C35: HDFC Bank Ltd. | E35: For MURLI STEEL CORPORATION
A36: A/c No.: | C36: 00082000057539
A37: Branch: | C37: Sree Bhumi
A38: IFSC: | C38: HDFC0004566 | E38: Authorised Signatory
A40: Terms: Goods once sold will not be taken back. Interest may be charged on delayed payment. Subject to Kolkata jurisdiction.
A41: E & O.E.

Sheet Lagan_15
A1: TAX INVOICE
A2: MURLI STEEL CORPORATION
H3: Original for Buyer/ Seller/ Transporter
A4: 9/12, Lal Bazar Street, Mercantile Building, 'B' Block, 1st Floor, Kolkata - 700001, India
A5: Phone: (033) 2210 1650 | Mobile: 9830242818 | Email: shradkakrania@gmail.com
A6: PAN: AKAPK4846L | GSTIN: 19AKAPK4846L1ZS
A8: BILLED TO PARTY | E8: INVOICE DETAILS
A9: Name: | C9: Lagan Engineering Co. Ltd. | E9: Invoice No.: | G9: MSC/15/2026-27
A10: Address: | C10: 14 KYD Street, Kolkata - 700016 | E10: Invoice Date: | G10: 46212
A11: GSTIN: | C11: 19AAACT9986F1ZP | E11: Payment Terms | G11: PROFORMA INVOICE
A12: Order No. | C12: P/2627/1126 | E12: Place of Supply: | G12: West Bengal
A13: Order Date | C13: 46148
A14: State: | B14: West Bengal | C14: Code: 19
A16: Delivery At: Lagan Engineering Co. Ltd., c/o Angus Jute Mills, Bhadeshwar, W.B. | E16: Transport: Lorry | G16: Vehicel No. : WB 15C 3317
A18: SN | B18: Item Code | C18: Description | D18: HSN Code | E18: No. of Pcs. | F18: Qty (kg) | G18: Rate (INR/kg) | H18: Taxable Value (INR)
A19: 1 | B19: =Master_Items!B14 -> 09110BL | C19: =Master_Items!C14 -> BRIGHT M.S. 1" DIA. TOLERANCE -0.005"/-0.008". LENGTH: 8-12 FT (En3B-BS970:1955) | D19: 721550 | F19: 555 | G19: 70 | H19: =F19*G19 -> 38850
A20: 2 | B20: =Master_Items!B15 -> 09111BL | C20: =Master_Items!C15 -> BRIGHT MS 1.1/4" DIA. TOLERANCE -0.002"/-0.005". LENGTH: 20-21 FEET (En3B-BS970:1955) | D20: 721550 | F20: 556 | G20: 70 | H20: =F20*G20 -> 38920
A21: 3 | B21: =Master_Items!B9 -> 09283BL | C21: =Master_Items!C9 -> BRIGHT M.S. 1.1/2" DIA. TOLERANCE ON DIA. -0.002"/-0.005". LENGTH: 18-20 FEET (En3B-BS970:1955) | D21: 721550 | F21: 625 | G21: 70 | H21: =F21*G21 -> 43750
A22: 4 | B22: =Master_Items!B2 -> 09112BL | C22: =Master_Items!C2 -> BRIGHT M.S. 1.3/4" DIA. TOLERANCE ON DIA. -0.002"/-0.005". LENGTH: 19-20 FEET (En3B-BS970:1955) | D22: 721550 | F22: 540 | G22: 70 | H22: =F22*G22 -> 37800
B23: =Master_Items!B29 -> 09427BL | C23: =Master_Items!C29 -> M.S. ANGLE 3" X 3" X 1/4" (75X75X6 MM), LENGTH: 18-20 FT | D23: 721621 | F23: 780 | G23: 60 | H23: =F23*G23 -> 46800
B24: =Master_Items!B25 -> 09394BL | C24: M.S. FLAT BLACK 50 X 12 MM | D24: 721114 | F24: 297.6 | G24: 60 | H24: =F24*G24 -> 17856
C25: TOTAL WEIGHT | F25: =SUM(F19:F24) -> 3353.6
E27: Total Amount Before Tax | H27: =SUM(H19:H25) -> 223976
E28: Delivery Charges | H28: 16500
E29: Taxable Value | H29: =SUM(H27:H28) -> 240476
E30: Add: CGST @ 9% | H30: =$H$29*9% -> 21642.84
E31: Add: SGST @ 9% | H31: =$H$29*9% -> 21642.84
E32: Grand Total | H32: =SUM(H29:H31) -> 283761.68
A34: Total Invoice Amount in Words: Rupees Two Lakh Eighty-Three Thousand Seven Hundred Sixty-One Rupees and Sixty-Eight Paise Only
A36: Bank Details : | H36: Certified that the particulars given above are true and correct.
A37: Bank: | C37: HDFC Bank Ltd. | E37: For MURLI STEEL CORPORATION
A38: A/c No.: | C38: 00082000057539
A39: Branch: | C39: Sree Bhumi
A40: IFSC: | C40: HDFC0004566 | E40: Authorised Signatory
A42: Terms: Goods once sold will not be taken back. Interest may be charged on delayed payment. Subject to Kolkata jurisdiction.
A43: E & O.E.

Sheet Lagan_10
A1: TAX INVOICE
A2: MURLI STEEL CORPORATION
H3: Original for Buyer/ Seller/ Transporter
A4: 9/12, Lal Bazar Street, Mercantile Building, 'B' Block, 1st Floor, Kolkata - 700001, India
A5: Phone: (033) 2210 1650 | Mobile: 9830242818 | Email: shradkakrania@gmail.com
A6: PAN: AKAPK4846L | GSTIN: 19AKAPK4846L1ZS
A8: BILLED TO PARTY | E8: INVOICE DETAILS
A9: Name: | C9: Lagan Engineering Co. Ltd. | E9: Invoice No.: | G9: MSC/10/2026-27
A10: Address: | C10: 14 KYD Street, Kolkata - 700016 | E10: Invoice Date: | G10: 46161
A11: GSTIN: | C11: 19AAACT9986F1ZP | E11: Payment Terms | G11: PROFORMA INVOICE
A12: Order No. | C12: P/2627/1126 | E12: Place of Supply: | G12: West Bengal
A13: Order Date | C13: 46148
A14: State: | B14: West Bengal | C14: Code: 19
A16: Delivery At: Lagan Engineering Co. Ltd., c/o Angus Jute Mills, Bhadeshwar, W.B. | E16: Transport: Lorry | G16: Vehicel No. : WB41E 9287
A18: SN | B18: Item Code | C18: Description | D18: HSN Code | E18: No. of Pcs. | F18: Qty (kg) | G18: Rate (INR/kg) | H18: Taxable Value (INR)
A19: 1 | B19: 09112BL | C19: BRIGHT M.S. 1.3/4" DIA. TOLERANCE ON DIA. -0.002"/-0.005". LENGTH: 19-20 FEET | D19: 721550 | E19: 7 | F19: 503 | G19: 70 | H19: =F19*G19 -> 35210
A20: 2 | B20: 09113BL | C20: BRIGHT M.S. 2" DIA. TOLERANCE ON DIA. +0.005"/+0.008". LENGTH: 18.5 FEET G.B | D20: 721550 | E20: 5 | F20: 501 | G20: 70 | H20: =F20*G20 -> 35070
A21: 3 | B21: 09115BL | C21: BRIGHT M.S. 2.1/2" DIA. TOLERANCE ON DIA. -0.001"/-0.005". LENGTH: 8-12 FT | D21: 721550 | E21: 4 | F21: 667 | G21: 71 | H21: =F21*G21 -> 47357
A22: 4 | B22: 09158BL | C22: BRIGHT M.S. GB 45MM DIA. TOLERANCE ON DIA. | D22: 721550 | E22: 13 | F22: 1010 | G22: 70 | H22: =F22*G22 -> 70700
A23: 5 | B23: 09283BL | C23: BRIGHT M.S. 1.1/2" DIA. TOLERANCE ON DIA. -0.002"/-0.005". LENGTH: 18-20 FEET | D23: 721550 | E23: 11 | F23: 604 | G23: 70 | H23: =F23*G23 -> 42280
E28: Total Amount Before Tax | H28: =SUM(H19:H26) -> 230617
E29: Delivery Charges | H29: 0
E30: Taxable Value | H30: =SUM(H28:H29) -> 230617
E31: Add: CGST @ 9% | H31: =$H$30*9% -> 20755.53
E32: Add: SGST @ 9% | H32: =$H$30*9% -> 20755.53
E33: Grand Total | H33: =SUM(H30:H32) -> 272128.06
A35: Total Invoice Amount in Words: Rupees Two Lakh Seventy-Two Thousand One Hundred Twenty-Eight and Six Paise Only.
A37: Bank Details : | H37: Certified that the particulars given above are true and correct.
A38: Bank: | C38: HDFC Bank Ltd. | E38: For MURLI STEEL CORPORATION
A39: A/c No.: | C39: 82000057539
A40: Branch: | C40: Sree Bhumi
A41: IFSC: | C41: HDFC0004566 | E41: Authorised Signatory
A43: Terms: Goods once sold will not be taken back. Interest may be charged on delayed payment. Subject to Kolkata jurisdiction.
A44: E & O.E.

Sheet Lagan_9
A1: TAX INVOICE
A2: MURLI STEEL CORPORATION
H3: Original for Buyer/ Seller/ Transporter
A4: 9/12, Lal Bazar Street, Mercantile Building, 'B' Block, 1st Floor, Kolkata - 700001, India
A5: Phone: (033) 2210 1650 | Mobile: 9830242818 | Email: shradkakrania@gmail.com
A6: PAN: AKAPK4846L | GSTIN: 19AKAPK4846L1ZS
A8: BILLED TO PARTY | E8: INVOICE DETAILS
A9: Name: | C9: Lagan Engineering Co. Ltd. | E9: Invoice No.: | G9: MSC/09/2026-27
A10: Address: | C10: 14 KYD Street, Kolkata - 700016 | E10: Invoice Date: | G10: 46161
A11: GSTIN: | C11: 19AAACT9986F1ZP | E11: Payment Terms | G11: PROFORMA INVOICE
A12: Order No. | C12: P/2627/1111 & 1112 | E12: Place of Supply: | G12: West Bengal
A13: Order Date | C13: 46140
A14: State: | B14: West Bengal | C14: Code: 19
A16: Delivery At: Lagan Engineering Co. Ltd., c/o Angus Jute Mills, Bhadeshwar, W.B. | E16: Transport: Lorry | G16: Vehicel No. : WB41E 9287
A18: SN | B18: Item Code | C18: Description | D18: HSN Code | E18: No. of Pcs. | F18: Qty (kg) | G18: Rate (INR/kg) | H18: Taxable Value (INR)
A19: 1 | B19: 09822BL | C19: BRIGHT CK45 STEEL - 2.1/4" DIA. GB TOL ON OD +0.014"/+0.018", HARDNESS 204 TO 249 BHN | D19: 721550 | E19: 7 | F19: 912 | G19: 86 | H19: =F19*G19 -> 78432
A20: 2 | B20: 09824BL | C20: BRIGHT CK45 STEEL - 2" DIA. GB TOL ON OD +0.014"/+0.018", HARDNESS 204 TO 249 BHN | D20: 721550 | E20: 21 | F20: 2170 | G20: 85 | H20: =F20*G20 -> 184450
A21: 3 | B21: 09816BL | C21: 1.3/8" DIA BRIGHT CLASS IV STEEL (G.B) TOL ON DIA +0.008"/+0.012" | D21: 721550 | E21: 23 | F21: 1089 | G21: 85 | H21: =F21*G21 -> 92565
A22: 4 | B22: 09463BL | C22: EN-36 BLACK ROUND 65MM DIA. | D22: 72283022 | E22: 1 | F22: 36 | G22: 310 | H22: =F22*G22 -> 11160
A23: 5 | B23: 09464BL | C23: EN-36 BLACK ROUND 75MM DIA. | D23: 72283022 | E23: 1 | F23: 49 | G23: 310 | H23: =F23*G23 -> 15190
A24: 6 | B24: 09465BL | C24: EN-36 BLACK ROUND 85MM DIA. | D24: 72283022 | E24: 1 | F24: 59 | G24: 310 | H24: =F24*G24 -> 18290
E26: Total Amount Before Tax | H26: =SUM(H19:H24) -> 400087
E27: Delivery Charges | H27: 15000
E28: Taxable Value | H28: =SUM(H26:H27) -> 415087
E29: Add: CGST @ 9% | H29: =$H$28*9% -> 37357.83
E30: Add: SGST @ 9% | H30: =$H$28*9% -> 37357.83
E31: Grand Total | H31: =SUM(H28:H30) -> 489802.66
A33: Total Invoice Amount in Words: Rupees Four Lakh Eighty-Nine Thousand Eight Hundred Two Rupees and Sixty-Six Paise Only
A35: Bank Details : | H35: Certified that the particulars given above are true and correct.
A36: Bank: | C36: HDFC Bank Ltd. | E36: For MURLI STEEL CORPORATION
A37: A/c No.: | C37: 82000057539
A38: Branch: | C38: Sree Bhumi
A39: IFSC: | C39: HDFC0004566 | E39: Authorised Signatory
A41: Terms: Goods once sold will not be taken back. Interest may be charged on delayed payment. Subject to Kolkata jurisdiction.
A42: E & O.E.

Sheet birla_05
A1: TAX INVOICE
A3: MURLI STEEL CORPORATION
H4: Original for Buyer/ Seller/ Transporter
A5: 9/12, Lal Bazar Street, Mercantile Building, 'B' Block, 1st Floor, Kolkata - 700001, India
A6: Phone: (033) 2210 1650 | Mobile: 9830242818 | Email: shradkakrania@gmail.com
A7: PAN: ΑΚΑΡΚ4846L | GSTIN: 19AKAPK4846L1ZS
A9: BILLED TO PARTY | E9: INVOICE DETAILS
A10: Name: | C10: Birla Corporation Ltd., Unit Birla Jute Mill | E10: Invoice No.: | G10: MSC/05/2026-27
A11: Address: | C11: 9/1 R.N. Mukherjee Road, Kolkata 700001 | E11: Invoice Date: | G11: 46148
A12: GSTIN: | C12: 19AABCB2075J1ZN | E12: Payment Terms | G12: 30 DAYS
A13: Order No. | C13: CP/2627/00018 | E13: Place of Supply: | G13: West Bengal
A14: Order Date | C14: 46128
A15: State: | B15: West Bengal | C15: Code: 19
A17: Delivery At: Birla Jute Mill, P.O.Birlapur, 24 Parganas, West Bengal | E17: Transport: | F17: Lorry | G17: Vehicel No. : | H17: WB25E-8483
A19: SN | B19: Item Code | C19: Description | D19: HSN Code | E19: No. of Pcs. | F19: Qty (kg) | G19: Rate (INR/kg) | H19: Taxable Value (INR)
A20: 1 | B20: 12090119 | C20: M.S. Angle 40 x 40 x 6 mm | D20: 72162100 | F20: 251 | G20: 56 | H20: =F20*G20 -> 14056
E27: Total Amount Before Tax | H27: =SUM(H20:H25) -> 14056
E28: Delivery Charges | H28: 7800
E29: Taxable Value | H29: =SUM(H27:H28) -> 21856
E30: Add: CGST @ 9% | H30: =$H$29*9% -> 1967.04
E31: Add: SGST @ 9% | H31: =$H$29*9% -> 1967.04
E32: Grand Total | H32: =SUM(H29:H31) -> 25790.08
A34: Total Invoice Amount in Words: Rupees Thirty Nine Thousand Seven Hundred Sixty Six Only
A36: ` | H36: Certified that the particulars given above are true and correct.
A37: Bank: | C37: HDFC Bank Ltd. | E37: For MURLI STEEL CORPORATION
A38: A/c No.: | C38: 82000057539
A39: Branch: | C39: Sree Bhumi
A40: IFSC: | C40: HDFC0004566 | E40: Authorised Signatory
A42: Terms: Goods once sold will not be taken back. Interest may be charged on delayed payment. Subject to Kolkata jurisdiction.
A43: E & O.E.

Sheet birla_11
A1: TAX INVOICE
A2: MURLI STEEL CORPORATION
H3: Original for Buyer/ Seller/ Transporter
A4: 9/12, Lal Bazar Street, Mercantile Building, 'B' Block, 1st Floor, Kolkata - 700001, India
A5: Phone: (033) 2210 1650 | Mobile: 9830242818 | Email: shradkakrania@gmail.com
A6: PAN: AKAPK4846L | GSTIN: 19AKAPK4846L1ZS
A8: BILLED TO PARTY | E8: INVOICE DETAILS
A9: Name: | C9: Birla Corporation Ltd., Unit Birla Jute Mill | E9: Invoice No.: | G9: MSC/11/2026-27
A10: Address: | C10: 9/1 R.N. Mukherjee Road, Kolkata 700001 | E10: Invoice Date: | G10: 46175
A11: GSTIN: | C11: 19AABCB2075J1ZN | E11: Payment Terms | G11: 30 DAYS
A12: Order No. | C12: GN/2627/00737 | E12: Place of Supply: | G12: West Bengal
A13: Order Date | C13: 46169
A14: State: | B14: West Bengal | C14: Code: 19
A16: Delivery At: Birla Jute Mill, P.O.Birlapur, 24 Parganas, West Bengal | E16: Transport: Lorry | G16: Vehicel No. : WB-25F-3703
A18: SN | B18: Item Code | C18: Description | D18: HSN Code | E18: No. of Pcs. | F18: Qty (kg) | G18: Rate (INR/kg) | H18: Taxable Value (INR)
A19: 1 | B19: 12050040 | C19: G.I. FLAT 25 x 6 MM | D19: 72123010 | F19: 184.6 | G19: 77 | H19: =F19*G19 -> 14214.2
A20: 2 | B20: 12050039 | C20: G.I. FLAT 40 x 6 MM | D20: 72123010 | F20: 158.5 | G20: 77 | H20: =F20*G20 -> 12204.5
A21: 3 | B21: 12050041 | C21: G.I. FLAT 25 x 3 MM | D21: 72123010 | F21: 160.8 | G21: 79 | H21: =F21*G21 -> 12703.2
A22: 4 | B22: 12050038 | C22: G.I. FLAT 50 x 6 MM | D22: 72123010 | F22: 168.5 | G22: 77 | H22: =F22*G22 -> 12974.5
E27: Total Amount Before Tax | H27: =SUM(H19:H25) -> 52096.4
E28: Delivery Charges | H28: 4000
E29: Taxable Value | H29: =SUM(H27:H28) -> 56096.4
E30: Add: CGST @ 9% | H30: =$H$29*9% -> 5048.676
E31: Add: SGST @ 9% | H31: =$H$29*9% -> 5048.676
E32: Grand Total | H32: =SUM(H29:H31) -> 66193.752
A34: Total Invoice Amount in Words: Rupees Sixty-six thousand one hundred ninety-three and seventy-five paise Only.
A36: Bank Details : | H36: Certified that the particulars given above are true and correct.
A37: Bank: | C37: HDFC Bank Ltd. | E37: For MURLI STEEL CORPORATION
A38: A/c No.: | C38: 00082000057539
A39: Branch: | C39: Sree Bhumi
A40: IFSC: | C40: HDFC0004566 | E40: Authorised Signatory
A42: Terms: Goods once sold will not be taken back. Interest may be charged on delayed payment. Subject to Kolkata jurisdiction.
A43: E & O.E.

Sheet birla_12
A1: TAX INVOICE
A2: MURLI STEEL CORPORATION
H3: Original for Buyer/ Seller/ Transporter
A4: 9/12, Lal Bazar Street, Mercantile Building, 'B' Block, 1st Floor, Kolkata - 700001, India
A5: Phone: (033) 2210 1650 | Mobile: 9830242818 | Email: shradkakrania@gmail.com
A6: PAN: AKAPK4846L | GSTIN: 19AKAPK4846L1ZS
A8: BILLED TO PARTY | E8: INVOICE DETAILS
A9: Name: | C9: Birla Corporation Ltd., Unit Birla Jute Mill | E9: Invoice No.: | G9: MSC/12/2026-27
A10: Address: | C10: 9/1 R.N. Mukherjee Road, Kolkata 700001 | E10: Invoice Date: | G10: 46175
A11: GSTIN: | C11: 19AABCB2075J1ZN | E11: Payment Terms | G11: 30 DAYS
A12: Order No. | C12: GN/2627/00734 | E12: Place of Supply: | G12: West Bengal
A13: Order Date | C13: 46172
A14: State: | B14: West Bengal | C14: Code: 19
A16: Delivery At: Birla Jute Mill, P.O.Birlapur, 24 Parganas, West Bengal | E16: Transport: Lorry | G16: Vehicel No. : WB-25F-3703
A18: SN | B18: Item Code | C18: Description | D18: HSN Code | E18: No. of Pcs. | F18: Qty (kg) | G18: Rate (INR/kg) | H18: Taxable Value (INR)
A19: 1 | B19: 12110024 | C19: M.S. BRIGHT 1/4" DIA | D19: 72155010 | F19: 57.6 | G19: 75 | H19: =F19*G19 -> 4320
A20: 2 | B20: 12110048 | C20: M.S. BRIGHT 3/16" DIA | D20: 72155010 | F20: 60.8 | G20: 75 | H20: =F20*G20 -> 4560
E27: Total Amount Before Tax | H27: =SUM(H19:H25) -> 8880
E28: Delivery Charges | H28: 2000
E29: Taxable Value | H29: =SUM(H27:H28) -> 10880
E30: Add: CGST @ 9% | H30: =$H$29*9% -> 979.2
E31: Add: SGST @ 9% | H31: =$H$29*9% -> 979.2
E32: Grand Total | H32: =SUM(H29:H31) -> 12838.4
A34: Total Invoice Amount in Words: Twelve Thousand Eight Hundred Thirty-Eight and Forty Paise Only.
A36: Bank Details : | H36: Certified that the particulars given above are true and correct.
A37: Bank: | C37: HDFC Bank Ltd. | E37: For MURLI STEEL CORPORATION
A38: A/c No.: | C38: 00082000057539
A39: Branch: | C39: Sree Bhumi
A40: IFSC: | C40: HDFC0004566 | E40: Authorised Signatory
A42: Terms: Goods once sold will not be taken back. Interest may be charged on delayed payment. Subject to Kolkata jurisdiction.
A43: E & O.E.

Sheet birla_13
A1: TAX INVOICE
A2: MURLI STEEL CORPORATION
H3: Original for Buyer/ Seller/ Transporter
A4: 9/12, Lal Bazar Street, Mercantile Building, 'B' Block, 1st Floor, Kolkata - 700001, India
A5: Phone: (033) 2210 1650 | Mobile: 9830242818 | Email: shradkakrania@gmail.com
A6: PAN: AKAPK4846L | GSTIN: 19AKAPK4846L1ZS
A8: BILLED TO PARTY | E8: INVOICE DETAILS
A9: Name: | C9: Birla Corporation Ltd., Unit Birla Jute Mill | E9: Invoice No.: | G9: MSC/13/2026-27
A10: Address: | C10: 9/1 R.N. Mukherjee Road, Kolkata 700001 | E10: Invoice Date: | G10: 46194
A11: GSTIN: | C11: 19AABCB2075J1ZN | E11: Payment Terms | G11: 30 DAYS
A12: Order No. | C12: GN/2627/00950 | E12: Place of Supply: | G12: West Bengal
A13: Order Date | C13: 46184
A14: State: | B14: West Bengal | C14: Code: 19
A16: Delivery At: Birla Jute Mill, P.O.Birlapur, 24 Parganas, West Bengal | E16: Transport: Lorry | G16: Vehicel No. : WB-25F-3703
A18: SN | B18: Item Code | C18: Description | D18: HSN Code | E18: No. of Pcs. | F18: Qty (kg) | G18: Rate (INR/kg) | H18: Taxable Value (INR)
A19: 1 | B19: 12090114 | C19: M.S CHANNEL 3' x 1.1/2' | D19: 72161000 | E19: 2 | F19: 86 | G19: 56 | H19: =F19*G19 -> 4816
A20: 2 | B20: 12050011 | C20: M.S. FLAT 50 x 12 MM | D20: 72111400 | E20: 4 | F20: 104 | G20: 56.5 | H20: =F20*G20 -> 5876
E27: Total Amount Before Tax | H27: =SUM(H19:H25) -> 10692
E28: Delivery Charges | H28: 4000
E29: Taxable Value | H29: =SUM(H27:H28) -> 14692
E30: Add: CGST @ 9% | H30: =$H$29*9% -> 1322.28
E31: Add: SGST @ 9% | H31: =$H$29*9% -> 1322.28
E32: Grand Total | H32: =SUM(H29:H31) -> 17336.56
A34: Total Invoice Amount in Words: Rupees Seventeen thousand three hundred thirty-six and fifty-six paise only.
A36: Bank Details : | H36: Certified that the particulars given above are true and correct.
A37: Bank: | C37: HDFC Bank Ltd. | E37: For MURLI STEEL CORPORATION
A38: A/c No.: | C38: 00082000057539
A39: Branch: | C39: Sree Bhumi
A40: IFSC: | C40: HDFC0004566 | E40: Authorised Signatory
A42: Terms: Goods once sold will not be taken back. Interest may be charged on delayed payment. Subject to Kolkata jurisdiction.
A43: E & O.E.

Sheet birla_14
A1: TAX INVOICE
A2: MURLI STEEL CORPORATION
H3: Original for Buyer/ Seller/ Transporter
A4: 9/12, Lal Bazar Street, Mercantile Building, 'B' Block, 1st Floor, Kolkata - 700001, India
A5: Phone: (033) 2210 1650 | Mobile: 9830242818 | Email: shradkakrania@gmail.com
A6: PAN: AKAPK4846L | GSTIN: 19AKAPK4846L1ZS
A8: BILLED TO PARTY | E8: INVOICE DETAILS
A9: Name: | C9: Birla Corporation Ltd., Unit Birla Jute Mill | E9: Invoice No.: | G9: MSC/14/2026-27
A10: Address: | C10: 9/1 R.N. Mukherjee Road, Kolkata 700001 | E10: Invoice Date: | G10: 46194
A11: GSTIN: | C11: 19AABCB2075J1ZN | E11: Payment Terms | G11: 30 DAYS
A12: Order No. | C12: CP/2627/00133 | E12: Place of Supply: | G12: West Bengal
A13: Order Date | C13: 46193
A14: State: | B14: West Bengal | C14: Code: 19
A16: Delivery At: Birla Jute Mill, P.O.Birlapur, 24 Parganas, West Bengal | E16: Transport: Lorry | G16: Vehicel No. : WB 25F 3703
A18: SN | B18: Item Code | C18: Description | D18: HSN Code | E18: No. of Pcs. | F18: Qty (kg) | G18: Rate (INR/kg) | H18: Taxable Value (INR)
A19: 1 | B19: 12090107 | C19: M.S. PLATE 12 MM THICK | D19: 72085100 | E19: 4 | F19: 1465 | G19: 63.75 | H19: =F19*G19 -> 93393.75
E27: Total Amount Before Tax | H27: =SUM(H19:H25) -> 93393.75
E28: Delivery Charges | H28: 4500
E29: Taxable Value | H29: =SUM(H27:H28) -> 97893.75
E30: Add: CGST @ 9% | H30: =$H$29*9% -> 8810.4375
E31: Add: SGST @ 9% | H31: =$H$29*9% -> 8810.4375
E32: Grand Total | H32: =SUM(H29:H31) -> 115514.62
A34: Total Invoice Amount in Words: Rupees One Lakh Fifteen Thousand Five Hundred Fourteen and Sixty-Three Paise Only.
A36: Bank Details : | H36: Certified that the particulars given above are true and correct.
A37: Bank: | C37: HDFC Bank Ltd. | E37: For MURLI STEEL CORPORATION
A38: A/c No.: | C38: 00082000057539
A39: Branch: | C39: Sree Bhumi
A40: IFSC: | C40: HDFC0004566 | E40: Authorised Signatory
A42: Terms: Goods once sold will not be taken back. Interest may be charged on delayed payment. Subject to Kolkata jurisdiction.
A43: E & O.E.

Sheet birla_14_CN
A1: TAX INVOICE / CREDIT NOTE
A2: MURLI STEEL CORPORATION
H3: Original for Buyer/ Seller/ Transporter
A4: 9/12, Lal Bazar Street, Mercantile Building, 'B' Block, 1st Floor, Kolkata - 700001, India
A5: Phone: (033) 2210 1650 | Mobile: 9830242818 | Email: shradkakrania@gmail.com
A6: PAN: AKAPK4846L | GSTIN: 19AKAPK4846L1ZS
A8: BILLED TO PARTY | E8: INVOICE DETAILS
A9: Name: | C9: Birla Corporation Ltd., Unit Birla Jute Mill | E9: Invoice No.: | G9: MSC/CN/01/2026-27
A10: Address: | C10: 9/1 R.N. Mukherjee Road, Kolkata 700001 | E10: Invoice Date: | G10: 46195
A11: GSTIN: | C11: 19AABCB2075J1ZN | E11: Payment Terms
A12: Order No. | C12: CP/2627/00133 | E12: Place of Supply: | G12: West Bengal
A13: Order Date | C13: 46193
A14: State: | B14: West Bengal | C14: Code: 19
A16: Delivery At: Birla Jute Mill, P.O.Birlapur, 24 Parganas, West Bengal | E16: Transport: Lorry | G16: Vehicel No. : WB 25F 3703
A18: SN | B18: Item Code | C18: Description | D18: HSN Code | E18: No. of Pcs. | F18: Qty (kg) | G18: Rate (INR/kg) | H18: Taxable Value (INR)
A19: 1 | B19: 12090107 | C19: M.S. PLATE 12 MM THICK * | D19: 72085100 | F19: 15 | G19: 63.75 | H19: =F19*G19 -> 956.25
A26: * Being the material received short at your end against bill no. MSC/14/2026-27 dated 21-06-2026.
E28: Total Amount Before Tax | H28: =SUM(H19:H24) -> 956.25
E29: Delivery Charges
E30: Taxable Value | H30: =SUM(H28:H29) -> 956.25
E31: Add: CGST @ 9% | H31: =$H$30*9% -> 86.0625
E32: Add: SGST @ 9% | H32: =$H$30*9% -> 86.0625
E33: Grand Total | H33: =SUM(H30:H32) -> 1128.375
A35: Total Invoice Amount in Words: Rupees One Thousand One Hundred Twenty-Eight Rupees and Thirty-Eight Paise only.
A37: Bank Details : | H37: Certified that the particulars given above are true and correct.
A38: Bank: | C38: HDFC Bank Ltd. | E38: For MURLI STEEL CORPORATION
A39: A/c No.: | C39: 00082000057539
A40: Branch: | C40: Sree Bhumi
A41: IFSC: | C41: HDFC0004566 | E41: Authorised Signatory
A43: Terms: Goods once sold will not be taken back. Interest may be charged on delayed payment. Subject to Kolkata jurisdiction.
A44: E & O.E.
